tests/__init__.py
tests/test_things3.py
tests/test_things3_api.py
tests/test_things3_cli.py
tests/test_things3_kanban.py
things3/__init__.py
things3/things3.py
things3/things3_api.py
things3/things3_app.py
things3/things3_appstore.py
things3/things3_cli.py
things3/things3_kanban.py
things3/things3_opml.py
things3_api-2.7.0.data/data/resources/android-icon-144x144.png
things3_api-2.7.0.data/data/resources/android-icon-192x192.png
things3_api-2.7.0.data/data/resources/android-icon-36x36.png
things3_api-2.7.0.data/data/resources/android-icon-48x48.png
things3_api-2.7.0.data/data/resources/android-icon-72x72.png
things3_api-2.7.0.data/data/resources/android-icon-96x96.png
things3_api-2.7.0.data/data/resources/apple-icon-114x114.png
things3_api-2.7.0.data/data/resources/apple-icon-120x120.png
things3_api-2.7.0.data/data/resources/apple-icon-144x144.png
things3_api-2.7.0.data/data/resources/apple-icon-152x152.png
things3_api-2.7.0.data/data/resources/apple-icon-180x180.png
things3_api-2.7.0.data/data/resources/apple-icon-57x57.png
things3_api-2.7.0.data/data/resources/apple-icon-60x60.png
things3_api-2.7.0.data/data/resources/apple-icon-72x72.png
things3_api-2.7.0.data/data/resources/apple-icon-76x76.png
things3_api-2.7.0.data/data/resources/apple-icon-precomposed.png
things3_api-2.7.0.data/data/resources/apple-icon.png
things3_api-2.7.0.data/data/resources/chart.bundle.min.js
things3_api-2.7.0.data/data/resources/chart.css
things3_api-2.7.0.data/data/resources/chartjs-plugin-labels.min.js
things3_api-2.7.0.data/data/resources/demo.sqlite3
things3_api-2.7.0.data/data/resources/fa.min.css
things3_api-2.7.0.data/data/resources/fa.min.js
things3_api-2.7.0.data/data/resources/favicon-16x16.png
things3_api-2.7.0.data/data/resources/favicon-32x32.png
things3_api-2.7.0.data/data/resources/favicon-96x96.png
things3_api-2.7.0.data/data/resources/favicon.ico
things3_api-2.7.0.data/data/resources/icon.icns
things3_api-2.7.0.data/data/resources/icon.png
things3_api-2.7.0.dist-info/LICENSE
things3_api-2.7.0.dist-info/METADATA
things3_api-2.7.0.dist-info/WHEEL
things3_api-2.7.0.dist-info/entry_points.txt
things3_api-2.7.0.dist-info/top_level.txt
things3_api-2.7.0.dist-info/RECORD
