Metadata-Version: 2.1
Name: things3-api
Version: 2.7.0
Summary: A simple read-only Kanban App for Things 3
Home-page: https://kanbanview.app
Author: Alexander Willner
Author-email: alex@willner.ws
License: UNKNOWN
Platform: UNKNOWN
Classifier: Development Status :: 4 - Beta
Classifier: Programming Language :: Python :: 3
Classifier: License :: OSI Approved :: Apache Software License
Classifier: Operating System :: MacOS :: MacOS X
Classifier: Environment :: Console
Classifier: Framework :: Flask
Classifier: Natural Language :: English
Requires-Python: >=3.6
License-File: LICENSE
